aleksis/apps/matrix/__init__.py
aleksis/apps/matrix/apps.py
aleksis/apps/matrix/filters.py
aleksis/apps/matrix/forms.py
aleksis/apps/matrix/frontend/index.js
aleksis/apps/matrix/frontend/messages/ar.json
aleksis/apps/matrix/frontend/messages/de.json
aleksis/apps/matrix/frontend/messages/en.json
aleksis/apps/matrix/frontend/messages/fr.json
aleksis/apps/matrix/frontend/messages/la.json
aleksis/apps/matrix/frontend/messages/nb_NO.json
aleksis/apps/matrix/frontend/messages/ru.json
aleksis/apps/matrix/frontend/messages/tr.json
aleksis/apps/matrix/frontend/messages/uk.json
aleksis/apps/matrix/locale/.keepdir
aleksis/apps/matrix/locale/ar/LC_MESSAGES/django.po
aleksis/apps/matrix/locale/de_DE/LC_MESSAGES/django.po
aleksis/apps/matrix/locale/fr/LC_MESSAGES/django.po
aleksis/apps/matrix/locale/la/LC_MESSAGES/django.po
aleksis/apps/matrix/locale/nb_NO/LC_MESSAGES/django.po
aleksis/apps/matrix/locale/ru/LC_MESSAGES/django.po
aleksis/apps/matrix/locale/tr_TR/LC_MESSAGES/django.po
aleksis/apps/matrix/locale/uk/LC_MESSAGES/django.po
aleksis/apps/matrix/migrations/0001_initial.py
aleksis/apps/matrix/migrations/0002_drop_onetoone.py
aleksis/apps/matrix/migrations/0003_add_managed_by_app_label.py
aleksis/apps/matrix/migrations/0004_drop_sites.py
aleksis/apps/matrix/migrations/__init__.py
aleksis/apps/matrix/model_extensions.py
aleksis/apps/matrix/models.py
aleksis/apps/matrix/preferences.py
aleksis/apps/matrix/rules.py
aleksis/apps/matrix/signals.py
aleksis/apps/matrix/tables.py
aleksis/apps/matrix/tasks.py
aleksis/apps/matrix/templates/matrix/room/list.html
aleksis/apps/matrix/tests/conftest.py
aleksis/apps/matrix/tests/synapse/homeserver.yaml
aleksis/apps/matrix/tests/synapse/matrix.aleksis.example.org.log.config
aleksis/apps/matrix/tests/synapse/matrix.aleksis.example.org.signing.key
aleksis/apps/matrix/tests/test_matrix.py
aleksis/apps/matrix/urls.py
aleksis/apps/matrix/util/matrix.py
aleksis/apps/matrix/views.py
aleksis_app_matrix-3.0.0.dist-info/LICENCE.rst
aleksis_app_matrix-3.0.0.dist-info/METADATA
aleksis_app_matrix-3.0.0.dist-info/WHEEL
aleksis_app_matrix-3.0.0.dist-info/entry_points.txt
aleksis_app_matrix-3.0.0.dist-info/RECORD
